{
  "actions": [
    {
      "acted_at": "2014-12-16", 
      "references": [
        {
          "reference": "CR S6929", 
          "type": "consideration"
        }, 
        {
          "reference": "CR S6929", 
          "type": "text"
        }
      ], 
      "text": "Amendment SA 4126 proposed by Senator Pryor for Senator Brown.", 
      "type": "action"
    }, 
    {
      "acted_at": "2014-12-16", 
      "how": "Unanimous Consent", 
      "references": [], 
      "result": "pass", 
      "text": "Amendment SA 4126 agreed to in Senate by Unanimous Consent.", 
      "type": "vote", 
      "vote_type": "vote", 
      "where": "s"
    }
  ], 
  "amendment_id": "samdt4126-113", 
  "amendment_type": "samdt", 
  "amends_amendment": null, 
  "amends_bill": {
    "bill_id": "sres226-113", 
    "bill_type": "sres", 
    "congress": 113, 
    "number": 226
  }, 
  "amends_treaty": null, 
  "chamber": "s", 
  "congress": "113", 
  "description": null, 
  "introduced_at": "2014-12-16", 
  "number": 4126, 
  "proposed_at": "2014-12-16", 
  "purpose": "To amend the preamble.", 
  "sponsor": {
    "district": null, 
    "name": "Brown, Sherrod", 
    "state": "OH", 
    "thomas_id": "00136", 
    "title": "Sen", 
    "type": "person"
  }, 
  "status": "pass", 
  "status_at": "2014-12-16", 
  "updated_at": "2015-01-02T13:16:02-05:00"
}